tekstialue/__init__.py
tekstialue/__main__.py
tekstialue/cli.py
tekstialue/tekstialue.py
tekstialue-2023.10.21.dist-info/LICENSE
tekstialue-2023.10.21.dist-info/METADATA
tekstialue-2023.10.21.dist-info/WHEEL
tekstialue-2023.10.21.dist-info/entry_points.txt
tekstialue-2023.10.21.dist-info/top_level.txt
tekstialue-2023.10.21.dist-info/RECORD
